safeexecute/__init__.py
safeexecute-0.0.22.dist-info/licenses/LICENSE
safeexecute-0.0.22.dist-info/METADATA
safeexecute-0.0.22.dist-info/WHEEL
safeexecute-0.0.22.dist-info/top_level.txt
safeexecute-0.0.22.dist-info/RECORD
