Metadata-Version: 2.4
Name: safeexecute
Version: 0.0.22
Summary: Safe way to execute Python code with containerization.
Author: Josh XT
Author-email: josh@devxt.com
Requires-Python: >=3.10
License-File: LICENSE
Requires-Dist: docker
Dynamic: author
Dynamic: author-email
Dynamic: description
Dynamic: description-content-type
Dynamic: license-file
Dynamic: requires-dist
Dynamic: requires-python
Dynamic: summary
